moinNLP/__init__.py
moinNLP/utils/__init__.py
moinNLP/utils/zh_num2int.py
moinNLP/utils/repetition/__init__.py
moinNLP/utils/repetition/repetition.py
moinNLP/utils/repetition/white.txt
moinNLP-1.0.4.dist-info/METADATA
moinNLP-1.0.4.dist-info/WHEEL
moinNLP-1.0.4.dist-info/top_level.txt
moinNLP-1.0.4.dist-info/RECORD
