Metadata-Version: 2.1
Name: moinNLP
Version: 1.0.4
Summary: 开发工具
Home-page: https://pypi.org/
Author: moin
Author-email: shaozhuquan@moinai.com
License: MIT
Platform: UNKNOWN
Requires-Python: >=3
